posted/__init__.py
posted/base.py
posted/scrap/__init__.py
posted/scrap/reactive_dag.py
posted/tests/__init__.py
posted/tests/common.py
posted/tests/utils.py
posted-0.1.5.dist-info/LICENSE
posted-0.1.5.dist-info/METADATA
posted-0.1.5.dist-info/WHEEL
posted-0.1.5.dist-info/top_level.txt
posted-0.1.5.dist-info/RECORD
