Metadata-Version: 2.1
Name: posted
Version: 0.1.5
Summary: Interfacing with message-broker functionality
Home-page: https://github.com/i2mint/posted
License: mit
Platform: any
License-File: LICENSE
Requires-Dist: i2
